{
	"name": "باران",
	"lastName": "عظیمی",
	"phoneNumber": "09168125753",
	"email": "example@gmail.com",
	"gender": "Female",
	"birthdate": "06/10/2005 00:00:00",
	"age": 19,
	"fatherName": "بب",
	"isIranian": true,
	"nationalCode": "1981069845",
	"insuranceId": 3,
	"supplementalInsuranceId": 6,
	"residenceProvince": "ثثثثقق",
	"residenceCity": "لاااا",
	"residenceAddress": "صقصقصقصقص",
	"residencePostalCode": "2336525852",
	"educationLevel": "Bachelor",
	"fixedPhoneNumber": "06344568498",
	"isMarried": true,
	"balance": 10000
}
